{
  "name": "@std/log",
  "version": "0.224.5",
  "exports": {
    ".": "./mod.ts",
    "./base-handler": "./base_handler.ts",
    "./console-handler": "./console_handler.ts",
    "./critical": "./critical.ts",
    "./debug": "./debug.ts",
    "./error": "./error.ts",
    "./file-handler": "./file_handler.ts",
    "./formatters": "./formatters.ts",
    "./get-logger": "./get_logger.ts",
    "./info": "./info.ts",
    "./levels": "./levels.ts",
    "./logger": "./logger.ts",
    "./rotating-file-handler": "./rotating_file_handler.ts",
    "./setup": "./setup.ts",
    "./warn": "./warn.ts"
  }
}
