{
  "scriptId": "342",
  "url": "file:///Users/tomas.zijdemans/Code/deno_std/std_cb/assert/greater_or_equal.ts",
  "functions": [
    {
      "functionName": "",
      "ranges": [
        {
          "startOffset": 0,
          "endOffset": 1020,
          "count": 1
        }
      ],
      "isBlockCoverage": true
    },
    {
      "functionName": "assertGreaterOrEqual",
      "ranges": [
        {
          "startOffset": 765,
          "endOffset": 1019,
          "count": 0
        }
      ],
      "isBlockCoverage": false
    }
  ]
}